dis_tp/Harmonics.py
dis_tp/Initialize.py
dis_tp/InverseMellin.py
dis_tp/MassiveCoeffFunc.py
dis_tp/MasslessCoeffFunc.py
dis_tp/MatchingFunc.py
dis_tp/ReadTxt.py
dis_tp/Splitting_funcs.py
dis_tp/TildeCoeffFunc.py
dis_tp/TildeCoeffFunc_light.py
dis_tp/__init__.py
dis_tp/configs.py
dis_tp/io.py
dis_tp/k_factors.py
dis_tp/logging.py
dis_tp/parameters.py
dis_tp/plot.py
dis_tp/runner.py
dis_tp/cli/__init__.py
dis_tp/cli/base.py
dis_tp/cli/compute.py
dis_tp/cli/grids.py
dis_tp/structure_functions/__init__.py
dis_tp/structure_functions/f2.py
dis_tp/structure_functions/fl.py
dis_tp/structure_functions/heavy_tools.py
dis_tp/structure_functions/light_tools.py
dis_tp-0.1.2.dist-info/entry_points.txt
dis_tp-0.1.2.dist-info/WHEEL
dis_tp-0.1.2.dist-info/METADATA
dis_tp-0.1.2.dist-info/RECORD
